DZDNeo4jTools/FullTextIndexBucketMultiProcessor.py
DZDNeo4jTools/LuceneTextCleanerTools.py
DZDNeo4jTools/TextIndexBucketProcessor.py
DZDNeo4jTools/__init__.py
DZDNeo4jTools/tools/__init__.py
DZDNeo4jTools/tools/nodes_to_buckets_distributor.py
DZDNeo4jTools/tools/run_periodic_iterate.py
DZDNeo4jTools/tools/wait_for_db_boot.py
DZDNeo4jTools/tools/wait_for_index_build_up.py
DZDNeo4jTools-0.0.1.dist-info/LICENSE.md
DZDNeo4jTools-0.0.1.dist-info/METADATA
DZDNeo4jTools-0.0.1.dist-info/WHEEL
DZDNeo4jTools-0.0.1.dist-info/top_level.txt
DZDNeo4jTools-0.0.1.dist-info/RECORD
