Metadata-Version: 2.1
Name: DZDNeo4jTools
Version: 0.0.1
Summary: Tool collection from the DZD Devs for working with a Neo4j Graph Database
Home-page: https://git.connect.dzd-ev.de/dzdpythonmodules/neo4j-tools
Author: Tim Bleimehl
Author-email: tim.bleimehl@helmholtz-muenchen.de
License: MIT
Requires-Python: >=3.6
License-File: LICENSE.md
Requires-Dist: py2neo
Requires-Dist: graphio
